Metadata-Version: 2.1
Name: Ftsa
Version: 0.0.4
Summary: A package for the clustering of financial time series data with the realized volatility allowed for.
Home-page: UNKNOWN
Author: rockfc
Author-email: rozen0maiden@126.com
License: UNKNOWN
Platform: UNKNOWN
Classifier: Programming Language :: Python :: 3
Classifier: License :: OSI Approved :: MIT License
Classifier: Operating System :: OS Independent
Requires-Python: >=3.6
